{
    "kind": "protocol",
    "name": "NSDatePickerCellDelegate",
    "module": "AppKit",
    "parents": [
        "objectivec.NSObject"
    ],
    "methods": [
        {
            "name": "datePickerCell",
            "params": [
                {
                    "variable_name": "datePickerCell",
                    "type": "AppKit.NSDatePickerCell *"
                },
                {
                    "name": "validateProposedDateValue",
                    "variable_name": "proposedDateValue",
                    "type": "Foundation.NSDate * *"
                },
                {
                    "name": "timeInterval",
                    "variable_name": "proposedTimeInterval",
                    "type": "Foundation.NSTimeInterval *"
                }
            ],
            "return_type": "void"
        }
    ]
}
