{
    "kind": "alias",
    "name": "NSDatePickerStyle",
    "module": "AppKit",
    "target_type": "NSUInteger",
    "values": [
        {
            "name": "NSDatePickerStyleClockAndCalendar",
            "value": "1",
            "module": "AppKit"
        },
        {
            "name": "NSDatePickerStyleTextField",
            "value": "2",
            "module": "AppKit"
        },
        {
            "name": "NSDatePickerStyleTextFieldAndStepper",
            "value": "0",
            "module": "AppKit"
        }
    ]
}
